spice_mcp/__init__.py
spice_mcp/config.py
spice_mcp/polars_utils.py
spice_mcp/py.typed
spice_mcp/adapters/__init__.py
spice_mcp/adapters/http_client.py
spice_mcp/adapters/dune/__init__.py
spice_mcp/adapters/dune/admin.py
spice_mcp/adapters/dune/cache.py
spice_mcp/adapters/dune/client.py
spice_mcp/adapters/dune/extract.py
spice_mcp/adapters/dune/helpers.py
spice_mcp/adapters/dune/query_wrapper.py
spice_mcp/adapters/dune/transport.py
spice_mcp/adapters/dune/types.py
spice_mcp/adapters/dune/typing_utils.py
spice_mcp/adapters/dune/urls.py
spice_mcp/adapters/dune/user_agent.py
spice_mcp/adapters/spellbook/__init__.py
spice_mcp/adapters/spellbook/explorer.py
spice_mcp/core/__init__.py
spice_mcp/core/errors.py
spice_mcp/core/models.py
spice_mcp/core/ports.py
spice_mcp/logging/query_history.py
spice_mcp/mcp/__init__.py
spice_mcp/mcp/server.py
spice_mcp/mcp/tools/__init__.py
spice_mcp/mcp/tools/base.py
spice_mcp/mcp/tools/execute_query.py
spice_mcp/observability/__init__.py
spice_mcp/observability/logging.py
spice_mcp/service_layer/__init__.py
spice_mcp/service_layer/discovery_service.py
spice_mcp/service_layer/query_admin_service.py
spice_mcp/service_layer/query_service.py
spice_mcp/service_layer/verification_service.py
spice_mcp-0.1.8.dist-info/METADATA
spice_mcp-0.1.8.dist-info/WHEEL
spice_mcp-0.1.8.dist-info/entry_points.txt
spice_mcp-0.1.8.dist-info/licenses/LICENSE
spice_mcp-0.1.8.dist-info/RECORD
