Metadata-Version: 2.4
Name: spice-mcp
Version: 0.1.8
Summary: mcp server built ontop of dune api endpoint
Author-email: Evan-Kim2028 <ekcopersonal@gmail.com>
License-File: LICENSE
Classifier: Operating System :: OS Independent
Classifier: Programming Language :: Python :: 3
Classifier: Programming Language :: Python :: 3 :: Only
Classifier: Programming Language :: Python :: 3.13
Classifier: Typing :: Typed
Requires-Python: >=3.13
Requires-Dist: aiohttp>=3.9.5
Requires-Dist: fastmcp>=0.3.0
Requires-Dist: mcp>=0.9.0
Requires-Dist: polars>=1.35.1
Requires-Dist: requests>=2.31.0
Requires-Dist: rich-argparse>=1.5.2
Requires-Dist: rich>=13.3.3
